Metadata-Version: 2.1
Name: udkundoku
Version: 2.3.0
Summary: Classical Chinese to Modern Japanese Translator
Home-page: https://github.com/KoichiYasuoka/UD-Kundoku
Author: Koichi Yasuoka
Author-email: yasuoka@kanji.zinbun.kyoto-u.ac.jp
License: MIT
Project-URL: ud-ja-kanbun, https://corpus.kanji.zinbun.kyoto-u.ac.jp/gitlab/Kanbun/ud-ja-kanbun
Project-URL: Source, https://github.com/KoichiYasuoka/UD-Kundoku
Project-URL: Tracker, https://github.com/KoichiYasuoka/UD-Kundoku/issues
Keywords: udkanbun nlp
Classifier: License :: OSI Approved :: MIT License
Classifier: Programming Language :: Python :: 3
Classifier: Operating System :: OS Independent
Classifier: Topic :: Text Processing :: Linguistic
Classifier: Natural Language :: Japanese
Requires-Python: >=3.6
License-File: LICENSE.txt
